[
  {
    "listing": "/3_researches_hst.html",
    "items": []
  },
  {
    "listing": "/4_reviews.html",
    "items": [
      "/posts/4. Reviews/2022-12-23-Ebayesthresh.html"
    ]
  },
  {
    "listing": "/3_researches_stgcn.html",
    "items": [
      "/posts/3. Researches/STGCN/2022-12-30-STGCN-Toy Example.html"
    ]
  },
  {
    "listing": "/2_study_cgsp.html",
    "items": [
      "/posts/2. Let's Study/CGSP/2022-12-27-CGSP-Chap-12-2-1-PSD.html",
      "/posts/2. Let's Study/CGSP/2022-12-26-CGSP-Chap-12-2-Weakly Stationary Graph Processes.html",
      "/posts/2. Let's Study/CGSP/2022-12-24-CGSP-Chap-8-3-DFT.html"
    ]
  },
  {
    "listing": "/2_study_essays.html",
    "items": [
      "/posts/2. Let's Study/Essays/2022-01-12-Topology.html",
      "/posts/2. Let's Study/Essays/2023-01-11-Inequality.html",
      "/posts/2. Let's Study/Essays/2023-01-07-RealAnalysis.html"
    ]
  },
  {
    "listing": "/5_notes.html",
    "items": []
  },
  {
    "listing": "/1_codes_pl.html",
    "items": [
      "/posts/1. Codes/PyTorchLightning/2022-11-29-Lesson1.html"
    ]
  }
]